setup.py
wishbone_encode_flatten/__init__.py
wishbone_encode_flatten/flatten.py
wishbone_encode_flatten.egg-info/PKG-INFO
wishbone_encode_flatten.egg-info/SOURCES.txt
wishbone_encode_flatten.egg-info/dependency_links.txt
wishbone_encode_flatten.egg-info/entry_points.txt
wishbone_encode_flatten.egg-info/namespace_packages.txt
wishbone_encode_flatten.egg-info/not-zip-safe
wishbone_encode_flatten.egg-info/requires.txt
wishbone_encode_flatten.egg-info/top_level.txt