Metadata-Version: 1.1
Name: wishbone-encode-flatten
Version: 1.0.0
Summary: A Wishbone module which Flattens a dict structure of arbitrary depth into individual metric events.
Home-page: https://github.com/smetj/wishbone-encode-flatten
Author: Jelle Smet
Author-email: development@smetj.net
License: UNKNOWN
Download-URL: https://github.com/smetj/wishbone-input-livestatus/tarball/master
Platform: Linux
Classifier: Development Status :: 5 - Production/Stable
Classifier: License :: OSI Approved :: GNU General Public License v3 or later (GPLv3+)
Classifier: Programming Language :: Python
Classifier: Programming Language :: Python :: 2.7
Classifier: Programming Language :: Python :: Implementation :: PyPy
Classifier: Intended Audience :: Developers
Classifier: Intended Audience :: System Administrators
